geometadp/__init__.py
geometadp/md_manager.py
geometadp-0.1.0.dev0.dist-info/LICENSE
geometadp-0.1.0.dev0.dist-info/METADATA
geometadp-0.1.0.dev0.dist-info/WHEEL
geometadp-0.1.0.dev0.dist-info/top_level.txt
geometadp-0.1.0.dev0.dist-info/RECORD
