Metadata-Version: 2.1
Name: geometadp
Version: 0.1.0.dev0
Summary: Geophysical Metadata Picker
Home-page: UNKNOWN
Author: Maximilian Weigand
Author-email: mweigand@geo.uni-bonn.de
License: MIT
Platform: UNKNOWN
Requires-Dist: dicttoxml
Requires-Dist: jupyter
Requires-Dist: ipywidgets
Requires-Dist: PyQT5
